{
  "configs": [
    "implementation.xml",
    "interface.xml"
  ],
  "secureProperties": [],
  "redeploymentEnabled": true,
  "name": "com.mycompany:gs_diy_4-1_accountsapi-implementation:1.0.0-SNAPSHOT",
  "minMuleVersion": "4.3.0",
  "requiredProduct": "MULE_EE",
  "classLoaderModelLoaderDescriptor": {
    "id": "mule",
    "attributes": {
      "exportedPackages": [],
      "exportedResources": [
        "application-types.xml",
        "examples/accounts_out.json",
        "implementation.xml",
        "interface.xml",
        "log4j2.xml"
      ]
    }
  },
  "bundleDescriptorLoader": {
    "id": "mule",
    "attributes": {}
  }
}